<?xml version="1.0" encoding="utf-8"?>
<Maintainer>
<Icon>https://github.com/Squidly271/community.applications/raw/master/webImages/Tripping-the-Rift-Chode_400x400%20(1).png</Icon>
<Profile>
Unraid fan and the author and maintainer of various plugins for Unraid including **Community Applications** and **Fix Common Problems**, along with being a major contributor to the forums at large.  I am of the belief that plugins carry an extra burden of support due to their nature and will endeavor to fix any problems with them ASAP.  Occasionally sarcastic and always a twisted sense of humour.
</Profile>
<DonateLink>https://www.icrc.org/en/donate/ukraine-0</DonateLink>
<DonateText>Support the Red Cross in the Ukraine</DonateText>
<Photo>https://raw.githubusercontent.com/Squidly271/community.applications/master/webImages/20191221_193714.jpg</Photo>
<Video>https://www.youtube.com/watch?v=WMxGVfk09lU</Video>
</Maintainer>

